{
  "forum": "/bug",
  "title": "tsefsjdf",
  "content": "dfgsdlkjfgsdf\ng\nsdfg\nsd\nfg\n\nsdfglksjdhfgsdfg sdfgljshdf skdjfhsk djgh lskdfjgh skldg ksdfhlaksdjfhsdfalksdfjh askd. as fas fasdfha dsklh afhjlsdlfh ahlsf ajshd k. askdfjah slkdfalskd a. a sf has fwioeufahweoifu ;Kmcnzxcv aleiradjf oasuihfbpaienqwe asiofuhdps9fiohja qwiejrnAKSFJNASDKNFSDJAHSODFIUAHDFJKLAJJk;jsdflajsdfhaosldfkja sdbfkLKJkls;dfjksd gfhas dkfjnalksdgdghs dfklasdfhaksjdhgf siugahei ufhaweifuhasidufhadfjhaksdjfhksadj fhaslkdfjahskdfjhsalkdjf",
  "username": "adminn",
  "date": "2022-04-13T22:23:05.539Z",
  "id": 1649888585539,
  "vote": 0,
  "usersvote": [],
  "comments": []
}